hackernews_cli-0.0.1.post5.dist-info/RECORD
hackernews_cli-0.0.1.post5.dist-info/METADATA
hackernews_cli-0.0.1.post5.dist-info/metadata.json
hackernews_cli-0.0.1.post5.dist-info/WHEEL
hackernews_cli-0.0.1.post5.dist-info/DESCRIPTION.rst
hackernews_cli-0.0.1.post5.dist-info/entry_points.txt
hackernews_cli-0.0.1.post5.dist-info/top_level.txt
hncli/config.py
hncli/_version.py
hncli/cli.py
hncli/__init__.py
