Metadata-Version: 2.0
Name: hackernews-cli
Version: 0.0.1.post5
Summary: Read HackerNews lika a hacker
Home-page: https://github.com/kamilchm/developer-experience
Author: Kamil Chmielewski
Author-email: kamil.chm@gmail.com
License: Apache License (2.0)
Platform: UNKNOWN
Classifier: Development Status :: 3 - Alpha
Classifier: Environment :: Console
Classifier: Intended Audience :: Developers
Classifier: License :: OSI Approved :: Apache Software License
Classifier: Natural Language :: English
Classifier: Operating System :: POSIX :: Linux
Classifier: Programming Language :: Python :: 2.7
Requires-Dist: click (==3.3)
Requires-Dist: HackerNews (==2.0.0)
Requires-Dist: anyconfig (==0.0.5)
